{
  "Login": "Login",
  "Nav": "Nav",
  "Profile-page": "Profile-page",
  "Profile_Page": "Profile_Page",
  "about-page-title": "about-page-title",
  "button-translate": "button-translate",
  "button-translate-short": "button-translate-short",
  "button_translate": "button_translate",
  "comment-not-exist": "comment-not-exist",
  "comment-text": "comment-text",
  "comment-title": "comment-title",
  "dddd": "dddd",
  "decrement": "decrement",
  "error": "error",
  "error-gen-error-button": "error-gen-error-button",
  "error-in-comment-creator": "error-in-comment-creator",
  "footer": "footer",
  "form": "form",
  "form-field-button-submit": "form-field-button-submit",
  "form-field-button-submite": "form-field-button-submite",
  "form-field-input-placeholder-login": "form-field-input-placeholder-login",
  "form-field-input-placeholder-password": "form-field-input-placeholder-password",
  "form-field-label-title-login": "form-field-label-title-login",
  "form-field-label-title-name": "form-field-label-title-name",
  "form-field-label-title-password": "form-field-label-title-password",
  "form-title-login-modal": "form-title-login-modal",
  "hello": "hello",
  "increment": "increment",
  "main-page-title": "main-page-title",
  "menu-main-link-login": "menu-main-link-login",
  "menu-main-link-logout": "menu-main-link-logout",
  "menu-main-link-reg": "menu-main-link-reg",
  "menu-navigation-link-about": "menu-navigation-link-about",
  "menu-navigation-link-main": "menu-navigation-link-main",
  "menu-top-link-about": "menu-top-link-about",
  "menu-top-link-login": "menu-top-link-login",
  "menu-top-link-main": "menu-top-link-main",
  "menu-top-link-reg": "menu-top-link-reg",
  "message-error-page": "message-error-page",
  "page-about-title": "page-about-title",
  "page-article": "page-article",
  "page-article-feed": "page-article-feed",
  "page-error-reloade": "page-error-reloade",
  "page-main-title": "page-main-title",
  "page-not-found": "page-not-found",
  "page-not-found-title": "page-not-found-title",
  "page_not_found_title": "page_not_found_title",
  "profile-edit-button": "profile-edit-button",
  "profile-reset-button": "profile-reset-button",
  "profile-save-button": "profile-save-button",
  "send-form": "send-form",
  "side-bar-toggle": "side-bar-toggle",
  "test-content-to-modal": "test-content-to-modal"
}
